[
  {
    "name": "Q-Bact injection 1gm",
    "category": "MEDICINE",
    "price": 370
  },
  {
    "name": "Q-Bact Injection 2gm",
    "category": "MEDICINE",
    "price": 745
  },
  {
    "name": "Q-Bact injection 2gm",
    "category": "MEDICINE",
    "price": 518
  },
  {
    "name": "Q-Palgite suspension 120ml",
    "category": "MEDICINE",
    "price": 180
  },
  {
    "name": "Q-Plex Syrup 120ml",
    "category": "MEDICINE",
    "price": 150
  },
  {
    "name": "Q-Well tablet 100 mg",
    "category": "MEDICINE",
    "price": 175
  },
  {
    "name": "Qalsan D Orange Flavour Tablet 30s",
    "category": "MEDICINE",
    "price": 102
  },
  {
    "name": "Qalsium-D Tablet",
    "category": "MEDICINE",
    "price": 280
  },
  {
    "name": "Qarshi Sharbat-e-Banafsha liquid 240ml",
    "category": "MEDICINE",
    "price": 160
  },
  {
    "name": "Qarshi Toot Siah Syrup 120ml",
    "category": "OTC",
    "price": 110
  },
  {
    "name": "Qazzo tablet 10mg",
    "category": "MEDICINE",
    "price": 520
  },
  {
    "name": "Qazzo tablet 20mg",
    "category": "MEDICINE",
    "price": 400
  },
  {
    "name": "Qbal IM / IV-INJ injection 500mcg",
    "category": "MEDICINE",
    "price": 342
  },
  {
    "name": "Qbal tablet 500mcg",
    "category": "MEDICINE",
    "price": 292.78
  },
  {
    "name": "QCO softgel capsule 100mg",
    "category": "MEDICINE",
    "price": 1964.7
  },
  {
    "name": "Qfolic tablet 400mcg",
    "category": "MEDICINE",
    "price": 160
  },
  {
    "name": "Qpro capsule 15mg",
    "category": "MEDICINE",
    "price": 147.88
  },
  {
    "name": "Qpro capsule 30mg",
    "category": "MEDICINE",
    "price": 227.72
  },
  {
    "name": "Qraise capsule 100mg",
    "category": "MEDICINE",
    "price": 660
  },
  {
    "name": "Qsartan Plus tablet 50mg / /12.5mg",
    "category": "MEDICINE",
    "price": 444.38
  },
  {
    "name": "Qsartan tablet 25mg",
    "category": "MEDICINE",
    "price": 158.48
  },
  {
    "name": "Qsartan Tablet 50mg",
    "category": "MEDICINE",
    "price": 279.06
  },
  {
    "name": "Quench Cream 50g",
    "category": "MEDICINE",
    "price": 225
  },
  {
    "name": "Qufen tablet 100mg",
    "category": "MEDICINE",
    "price": 291.75
  },
  {
    "name": "Qufen tablet 50mg",
    "category": "MEDICINE",
    "price": 48.5
  },
  {
    "name": "Quibron T/SR tablet 300mg",
    "category": "MEDICINE",
    "price": 64.2
  },
  {
    "name": "Quibron-T/SR tablet 300mg",
    "category": "MEDICINE",
    "price": 700.12
  },
  {
    "name": "Quinoflox eye drop 0.003",
    "category": "MEDICINE",
    "price": 95
  },
  {
    "name": "Quinoflox Injection 100mg 50ml",
    "category": "MEDICINE",
    "price": 150
  },
  {
    "name": "Quinoflox Tablet 500mg",
    "category": "MEDICINE",
    "price": 425
  },
  {
    "name": "Quinvaxem 0.5ml",
    "category": "MEDICINE",
    "price": 1800
  },
  {
    "name": "Quitin tablet 100mg",
    "category": "MEDICINE",
    "price": 215
  },
  {
    "name": "Qumic injection 500mg",
    "category": "MEDICINE",
    "price": 320
  },
  {
    "name": "Qumic Tablet 250mg",
    "category": "MEDICINE",
    "price": 210
  },
  {
    "name": "Qumic tablet 500mg",
    "category": "MEDICINE",
    "price": 310
  },
  {
    "name": "QUPIN tablet 25MG",
    "category": "MEDICINE",
    "price": 125.33
  },
  {
    "name": "Qusel tablet 100mg",
    "category": "MEDICINE",
    "price": 766
  },
  {
    "name": "Qusel Tablet 25mg",
    "category": "MEDICINE",
    "price": 641.01
  },
  {
    "name": "Qusel XR tablet 200 mg",
    "category": "MEDICINE",
    "price": 575
  },
  {
    "name": "Qutyl Tablet 200mg",
    "category": "MEDICINE",
    "price": 570
  },
  {
    "name": "Qzon injection im 1gm",
    "category": "MEDICINE",
    "price": 310
  },
  {
    "name": "Qzon injection iv 1g",
    "category": "MEDICINE",
    "price": 780
  },
  {
    "name": "Qzon IV Injection 1gm",
    "category": "MEDICINE",
    "price": 450
  }
]